kanidm/__init__.py
kanidm/exceptions.py
kanidm/models/__init__.py
kanidm/models/group.py
kanidm/models/oauth2_rs.py
kanidm/models/person.py
kanidm/models/service_account.py
kanidm/py.typed
kanidm/radius/__init__.py
kanidm/radius/radiusd.py
kanidm/radius/utils.py
kanidm/tokens.py
kanidm/types.py
kanidm/utils.py
pykanidm-1.0.0.dist-info/METADATA
pykanidm-1.0.0.dist-info/WHEEL
pykanidm-1.0.0.dist-info/RECORD
