Metadata-Version: 2.1
Name: pykanidm
Version: 1.0.0
Summary: Kanidm client library
Home-page: https://kanidm.com/
License: MPL-2.0
Keywords: kanidm,idm,api
Author: Simon Bordeyne
Author-email: simon.bordeyne@gmail.com
Requires-Python: >=3.9,<4.0
Classifier: Development Status :: 3 - Alpha
Classifier: License :: OSI Approved
Classifier: Operating System :: OS Independent
Classifier: Programming Language :: Python :: 3
Classifier: Programming Language :: Python :: 3.9
Classifier: Programming Language :: Python :: 3.10
Classifier: Programming Language :: Python :: 3.11
Classifier: Programming Language :: Python :: 3.12
Requires-Dist: Authlib (>=1.2.0,<2.0.0)
Requires-Dist: aiohttp (>=3.8.1,<4.0.0)
Requires-Dist: pydantic (>=2.0.0,<3.0.0)
Requires-Dist: toml (>=0.10.2,<0.11.0)
Project-URL: Repository, https://github.com/sbordeyne/kanidm
